cowait/__init__.py
cowait/__main__.py
cowait/version.py
cowait/cli/__init__.py
cowait/cli/config.py
cowait/cli/const.py
cowait/cli/context.py
cowait/cli/docker_file.py
cowait/cli/errors.py
cowait/cli/logger.py
cowait/cli/settings_dict.py
cowait/cli/task_image.py
cowait/cli/utils.py
cowait/cli/app/__init__.py
cowait/cli/app/cluster.py
cowait/cli/app/context.py
cowait/cli/app/image.py
cowait/cli/app/notebook.py
cowait/cli/app/root.py
cowait/cli/app/task.py
cowait/cli/app/utils.py
cowait/cli/commands/__init__.py
cowait/cli/commands/agent.py
cowait/cli/commands/build.py
cowait/cli/commands/cluster.py
cowait/cli/commands/new_context.py
cowait/cli/commands/notebook.py
cowait/cli/commands/push.py
cowait/cli/commands/run.py
cowait/cli/commands/task.py
cowait/cli/commands/test.py
cowait/engine/__init__.py
cowait/engine/api.py
cowait/engine/cluster.py
cowait/engine/const.py
cowait/engine/errors.py
cowait/engine/utils.py
cowait/engine/docker/__init__.py
cowait/engine/docker/docker.py
cowait/engine/docker/task.py
cowait/engine/docker/utils.py
cowait/engine/docker/volumes.py
cowait/engine/kubernetes/__init__.py
cowait/engine/kubernetes/affinity.py
cowait/engine/kubernetes/errors.py
cowait/engine/kubernetes/kubernetes.py
cowait/engine/kubernetes/pod.py
cowait/engine/kubernetes/task.py
cowait/engine/kubernetes/utils.py
cowait/engine/kubernetes/volumes.py
cowait/engine/routers/__init__.py
cowait/engine/routers/local_port_router.py
cowait/engine/routers/router.py
cowait/engine/routers/traefik2_router.py
cowait/engine/routers/traefik_router.py
cowait/network/__init__.py
cowait/network/auth_middleware.py
cowait/network/client.py
cowait/network/conn.py
cowait/network/const.py
cowait/network/errors.py
cowait/network/rpc_client.py
cowait/network/server.py
cowait/network/utils.py
cowait/notebook/__init__.py
cowait/notebook/html_logger.py
cowait/notebook/html_repr.py
cowait/notebook/kernel.py
cowait/notebook/node.py
cowait/notebook/task.py
cowait/tasks/__init__.py
cowait-0.5.0.dist-info/LICENSE
cowait-0.5.0.dist-info/METADATA
cowait-0.5.0.dist-info/WHEEL
cowait-0.5.0.dist-info/entry_points.txt
cowait-0.5.0.dist-info/top_level.txt
cowait-0.5.0.dist-info/RECORD
