Metadata-Version: 2.1
Name: cowait
Version: 0.5.0
Summary: Cowait is a framework for creating containerized workflows with asynchronous Python.
Home-page: https://github.com/backtick-se/cowait
Author: Backtick Technologies
Requires-Python: >=3.7
License-File: LICENSE
Requires-Dist: docker (>=4)
Requires-Dist: kubernetes (<22,>=10)
Requires-Dist: nest-asyncio (>=1.4.1)
Requires-Dist: aiohttp (==3.7.4)
Requires-Dist: aiohttp-middlewares (>=1)
Requires-Dist: pytest (>=6)
Requires-Dist: alt-pytest-asyncio (>=0.5.3)
Requires-Dist: python-dotenv (>=0.15)
Requires-Dist: click (>=7)
Requires-Dist: PyYAML (>=5)
Requires-Dist: sty (==1.0.0-beta.12)
Requires-Dist: pytest-sugar (>=0.9)
Requires-Dist: pytest-cov (>=2)
Requires-Dist: dask (>=2)
Requires-Dist: distributed (>=2)
